{
  "\u001b[13;2~": "FindPrevious",
  "\u001b[1;3A": "MoveLinesUp",
  "\u001b[1;3B": "MoveLinesDown",
  "Alt-n": "NextTab|FirstTab",
  "Alt-p": "PreviousTab|LastTab",
  "Alt-Down": "MoveLinesDown",
  "Alt-G": "FindPrevious",
  "Alt-Left": "WordLeft",
  "Alt-Right": "WordRight",
  "Alt-Shift-Left": "SelectWordLeft",
  "Alt-Shift-Right": "SelectWordRight",
  "Alt-Up": "MoveLinesUp",
  "Alt-g": "FindNext",
  "Alt-q": "command:rewrapcomment",
  "Ctrl-Shift-Down": "SpawnMultiCursorDown",
  "Ctrl-Shift-Up": "SpawnMultiCursorUp",
  "Ctrl-Shift-d": "DuplicateLine",
  "Ctrl-Shift-k": "CutLine",
  "Ctrl-Shift-p": "CommandMode",
  "Ctrl-d": "SpawnMultiCursor",
  "Ctrl-g": "JumpLine",
  "Ctrl-h": "command-edit:replace ",
  "Ctrl-n": "command:newscratch",
  "Ctrl-o": "command-edit:tab ",
  "Ctrl-p": "command:fuzzyopen",
  "Ctrl-r": "command:reload",
  "Ctrl-w": "command:smartquit",
  "F3": "FindNext",
  "F9": "command:sortlines"
}
